{"name": "n-th integer divisible by a or b", "group": "E-Olymp - ADA October 18 - Binary Search", "url": "https://www.e-olymp.com/en/contests/13949/problems/137353", "interactive": false, "memoryLimit": 128, "timeLimit": 1000, "tests": [{"input": "2 5 10\n", "output": "16\n"}, {"input": "3 7 25\n", "output": "57\n"}], "testType": "single", "input": {"type": "stdin"}, "output": {"type": "stdout"}, "languages": {"java": {"mainClass": "Main", "taskClass": "NThIntegerDivisibleByAOrB"}}, "batch": {"id": "5b19cec5-26c9-4165-b746-a1efaa6ac45b", "size": 1}}